[
  {
    "backcolor": "#ffffff",
    "name": "Keyboardio Model 01 - Shajira UK",
    "author": "Farrago",
    "radii": "50px",
    "switchMount": "alps",
    "switchBrand": "matias",
    "switchType": "PG155B01",
    "pcb": true,
    "css": ".keyboardio { }\n\n.keyboardio-logo:after {\n    background: inherit;\n    content:'\\00a0'; \n    display:inline-block; \n    width: 2em; \n    height: 2em; \n    background-size: 2em; \n    background-image: url(http://67.media.tumblr.com/avatar_ddfdafa42fef_128.png);\n}\n"
  },
  [
    {
      "r": 10,
      "x": 4,
      "t": "#417841"
    },
    "£\n3\nF3",
    {
      "h": 1.05
    },
    "$\n4\nF4"
  ],
  [
    {
      "y": -0.9,
      "x": 3
    },
    "\"\n2\nF2"
  ],
  [
    {
      "y": -1,
      "x": 6,
      "h": 1.1
    },
    "%\n5\nF5"
  ],
  [
    {
      "y": -0.9,
      "x": 2,
      "h": 1.4
    },
    "!\n1\nF1"
  ],
  [
    {
      "y": -0.9,
      "x": 1,
      "h": 1.3
    },
    "\n\n⏾\n\n\n\nCaps"
  ],
  [
    {
      "y": -0.9,
      "x": 7,
      "fa": [
        0,
        0,
        1
      ],
      "h": 1.5
    },
    "|\n\\\nLED"
  ],
  [
    {
      "y": -0.3999999999999999,
      "x": 4,
      "f": 3
    },
    "\n\n{\n\n\n\nE"
  ],
  [
    {
      "y": -0.95,
      "x": 5,
      "f": 3
    },
    "\n\n}\n\n\n\nR"
  ],
  [
    {
      "y": -0.95,
      "x": 3,
      "f": 3
    },
    "\n\n@\n\n\n\nW"
  ],
  [
    {
      "y": -0.8999999999999999,
      "x": 6,
      "f": 3
    },
    "\n\n'\n\n\n\nT"
  ],
  [
    {
      "y": -0.6000000000000001,
      "x": 1,
      "fa": [
        0,
        0,
        2
      ]
    },
    "¬\n`\n☰",
    {
      "f": 3
    },
    "\n\n!\n\n\n\nQ"
  ],
  [
    {
      "y": -0.7,
      "x": 7,
      "f": 5,
      "fa": [
        0,
        0,
        1
      ],
      "h": 1.25
    },
    "\n\nHome\n\n\n\nPg Up"
  ],
  [
    {
      "y": -0.8999999999999999,
      "x": 4,
      "f": 3
    },
    "\n\n(\n\n\n\nD"
  ],
  [
    {
      "y": -0.9499999999999997,
      "x": 5,
      "n": true
    },
    "\n\n)\n\n\n\nF"
  ],
  [
    {
      "y": -0.9500000000000002,
      "x": 3
    },
    "\n\n$\n\n\n\nS"
  ],
  [
    {
      "y": -0.8999999999999999,
      "x": 6
    },
    "\n\n\"\n\n\n\nG"
  ],
  [
    {
      "y": -0.6000000000000001,
      "x": 1,
      "a": 6
    },
    "Tab",
    {
      "a": 4
    },
    "\n\n^\n\n\n\nA"
  ],
  [
    {
      "y": -0.6000000000000001,
      "x": 4,
      "h": 1.15
    },
    "\n\n[\n\n\n\nC"
  ],
  [
    {
      "y": -0.9500000000000002,
      "x": 5,
      "a": 6,
      "h": 1.1
    },
    "V\n\n]"
  ],
  [
    {
      "y": -0.9500000000000002,
      "x": 3,
      "a": 4,
      "h": 1.2
    },
    "\n\n%\n\n\n\nX"
  ],
  [
    {
      "y": -0.9500000000000002,
      "x": 7,
      "f": 5,
      "fa": [
        0,
        0,
        1
      ],
      "h": 1.25
    },
    "\n\nEnd\n\n\n\nPg Dwn"
  ],
  [
    {
      "y": -0.9500000000000002,
      "x": 6,
      "f": 3
    },
    "\n\n`\n\n\n\nB"
  ],
  [
    {
      "y": -0.6000000000000001,
      "x": 1,
      "fa": [
        0,
        0,
        1,
        0,
        0,
        0,
        0,
        1
      ]
    },
    "{\n[\nAlt-\n\n\n\n\nGR",
    {
      "f": 3
    },
    "\n\n#\n\n\n\nZ"
  ],
  [
    {
      "r": 22.5,
      "rx": 4,
      "ry": 9,
      "y": -3.9800000000000004,
      "x": -0.75,
      "f": 5,
      "fa": [
        0,
        0,
        1,
        1
      ]
    },
    "\n\n\nGUI\n\n\nDEL"
  ],
  [
    {
      "r": 30,
      "y": -1.0199999999999996,
      "x": -0.1499999999999999,
      "fa": [
        0,
        0,
        1,
        1,
        0,
        0,
        0,
        0,
        0,
        9
      ]
    },
    "\n\n\nSHIFT\n\n\n\n\n\n⭠"
  ],
  [
    {
      "rx": 8.5,
      "ry": 4.5,
      "y": 3.8499999999999996,
      "x": -1.5,
      "t": "#000000",
      "f": 9,
      "fa": [
        0,
        0,
        1,
        1,
        0,
        0,
        6
      ],
      "w": 1.5,
      "h": 1.5
    },
    "\n\n\nFN\n\n\nHOME"
  ],
  [
    {
      "r": 37.5,
      "rx": 4,
      "ry": 9,
      "y": -4.07,
      "x": 0.4500000000000002,
      "t": "#417841",
      "f": 5,
      "fa": [
        0,
        0,
        1,
        1
      ]
    },
    "\n\n\nCTRL\n\n\nTAB"
  ],
  [
    {
      "r": 45,
      "y": -1.1500000000000004,
      "x": 1.0199999999999996
    },
    "\n\n\nALT\n\n\nESC"
  ],
  [
    {
      "r": -45,
      "rx": 12,
      "y": -3.55,
      "x": -1.3599999999999994
    },
    "¬\n`\n\nGUI"
  ],
  [
    {
      "r": -37.5,
      "y": -0.9500000000000002,
      "x": -0.6899999999999995,
      "fa": [
        0,
        0,
        1,
        1,
        0,
        0,
        0,
        0,
        0,
        9
      ]
    },
    "\n\n\nCTRL\n\n\n\n\n\n↵"
  ],
  [
    {
      "r": -30,
      "rx": 8.5,
      "ry": 5,
      "y": 3.42,
      "x": 0.25,
      "t": "#000000",
      "f": 9,
      "fa": [
        0,
        0,
        1,
        1,
        0,
        0,
        6
      ],
      "w": 1.5,
      "h": 1.5
    },
    "\n\n\nFN\n\n\nEND"
  ],
  [
    {
      "rx": 12,
      "ry": 9,
      "y": -3.5199999999999996,
      "x": -0.009999999999999787,
      "t": "#417841",
      "f": 5,
      "fa": [
        0,
        0,
        1,
        1
      ]
    },
    "\n\n\nSHIFT\n\n\n\n\n\n␣"
  ],
  [
    {
      "r": -22.5,
      "rx": 12.08,
      "ry": 9.38,
      "y": -4,
      "x": 0.7200000000000006
    },
    "\n\n\nALT\n\n\nINS"
  ],
  [
    {
      "r": -10,
      "rx": 17,
      "ry": 0,
      "x": -6,
      "f": 3,
      "h": 1.05
    },
    "&\n7\nF7",
    "*\n8\nF8"
  ],
  [
    {
      "y": -0.9,
      "x": -7,
      "h": 1.1
    },
    "^\n6\nF6",
    {
      "x": 2,
      "h": 1.1
    },
    "(\n9\nF9"
  ],
  [
    {
      "y": -0.9,
      "x": -3,
      "h": 1.4
    },
    ")\n0\nF10"
  ],
  [
    {
      "y": -0.9,
      "x": -2,
      "h": 1.3
    },
    "\n\nF11\n\n\n\nNUM LOCK"
  ],
  [
    {
      "y": -0.9,
      "x": -8,
      "f": 5,
      "fa": [
        0,
        0,
        1
      ],
      "h": 1.5
    },
    "\n\nVersion\n\n\n\nGUI ⇆ ALT"
  ],
  [
    {
      "y": -0.3999999999999999,
      "x": -5,
      "f": 3
    },
    "\n\n*\n\n\n\nI"
  ],
  [
    {
      "y": -0.95,
      "x": -6
    },
    "\n\n&\n\n\n\nU"
  ],
  [
    {
      "y": -0.8500000000000001,
      "x": -7,
      "a": 6
    },
    "Y",
    {
      "x": 2,
      "a": 4
    },
    "\n\n~\n\n\n\nO"
  ],
  [
    {
      "y": -0.6000000000000001,
      "x": -3
    },
    "\n\n/\n\n\n\nP",
    "~\n#\nF12"
  ],
  [
    {
      "y": -0.7,
      "x": -8,
      "f": 5,
      "h": 1.25
    },
    "+\n="
  ],
  [
    {
      "y": -0.8999999999999999,
      "x": -5,
      "f": 3
    },
    "\n\n↑\n\n\n\nK"
  ],
  [
    {
      "y": -0.9499999999999997,
      "x": -6,
      "n": true
    },
    "\n\n↓\n\n\n\nJ"
  ],
  [
    {
      "y": -0.8500000000000001,
      "x": -7,
      "fa": [
        0,
        0,
        2
      ]
    },
    "\n\n←\n\n\n\nH",
    {
      "x": 2,
      "f": 3
    },
    "\n\n→\n\n\n\nL"
  ],
  [
    {
      "y": -0.6000000000000001,
      "x": -3
    },
    ":\n;",
    "@\n'"
  ],
  [
    {
      "y": -0.6000000000000001,
      "x": -5,
      "h": 1.15
    },
    "<\n,"
  ],
  [
    {
      "y": -0.9500000000000002,
      "x": -6,
      "f": 3,
      "h": 1.1
    },
    "\n\n|\n\n\n\nM"
  ],
  [
    {
      "y": -0.8999999999999999,
      "x": -8,
      "f": 5,
      "h": 1.25
    },
    "_\n-"
  ],
  [
    {
      "y": -0.9500000000000002,
      "x": -7,
      "f": 3
    },
    "\n\n\\\n\n\n\nN",
    {
      "x": 2,
      "h": 1.2
    },
    ">\n."
  ],
  [
    {
      "y": -0.6000000000000001,
      "x": -3
    },
    "?\n/",
    {
      "fa": [
        0,
        0,
        1,
        0,
        0,
        0,
        0,
        1
      ]
    },
    "}\n]\nALT-\n\n\n\n\nGR"
  ]
]